{
    "video_info": {
        "id": "4EfUOhvTFyE",
        "channelTitle": "Howwork X \u516d\u6307\u6df5",
        "title": "\u6c92\u60f3\u5230\u6703\u8b8a\u9019\u6a23\ud83e\udd2f",
        "description": "",
        "likeCount": "11316",
        "commentCount": "137",
        "viewCount": "317992"
    },
    "comments": [
        {
            "reply_id": "UgwUCdMwQsX2BYjl0514AaABAg",
            "reply_content": "\u6700\u5f8c\u90a3\u5e55\u597d\u8272"
        },
        {
            "reply_id": "UgyMaB8rjeT9r2TJ3UJ4AaABAg",
            "reply_content": "\u6211\u5230\u6700\u5f8c\u4e00\u523b\u4ee5\u524d\u90fd\u5728\u731c\u4e5d\u6307\u6df5\u6703\u5728\u54ea\u88e1\u653e\u7279\u6548\u7684\u8aaa..."
        },
        {
            "reply_id": "Ugx1O10Wiv6aQ1HIYnx4AaABAg",
            "reply_content": "\u6211\u6709\u4e00\u500b\u5927\u81bd\u7684\u60f3\u6cd5\u2026"
        },
        {
            "reply_id": "Ugxxl6FtB1hwgxI0wj94AaABAg",
            "reply_content": "\u90a3\u5fae\u6ce2\u7210\u548c\u6211\u5bb6\u7684\u4e00\u6a21\u4e00\u6a23"
        },
        {
            "reply_id": "UgxsVPbmKiQm5ba8b4R4AaABAg",
            "reply_content": "\u5316\u5de5\u68c9\u82b1\u7cd6"
        },
        {
            "reply_id": "UgzGGh6ctN3i5MhS6Md4AaABAg",
            "reply_content": "\u9019\u7279\u6548\u505a\u7684\u771f\u597d"
        },
        {
            "reply_id": "UgxGm2J75GBdAH93HhJ4AaABAg",
            "reply_content": "\u9177"
        },
        {
            "reply_id": "Ugy0IA6uG1ZSjuTsszN4AaABAg",
            "reply_content": "\u6211\u60f3\u8981\u9019\u7a2e\u8001\u95c6"
        },
        {
            "reply_id": "UgxJI4t6qh2GHPEAhGF4AaABAg",
            "reply_content": "\u9019\u7279\u6548\u771f\u53b2\u5bb3"
        },
        {
            "reply_id": "Ugw3IdL-Urd8rNVrB9d4AaABAg",
            "reply_content": "\u5982\u679c\u662f\u516d\u6307\u6df5 \u90a3\u4e00\u5b9a\u662f\u7279\u6548"
        },
        {
            "reply_id": "Ugx6HPo0b3vLuCiVnAR4AaABAg",
            "reply_content": "\u4ee5\u5f8c\u62ab\u85a9\u4e0d\u8981\u653e\u8d77\u53f8\uff0c\u76f4\u63a5\u653e\u68c9\u82b1\u7cd6"
        },
        {
            "reply_id": "Ugxm-qFPrB-PI5ycn0F4AaABAg",
            "reply_content": "\u5225\u9a19\u6211\u4e86 \u9019\u4e00\u5b9a\u662f\u7279\u6548"
        },
        {
            "reply_id": "UgyiuhoxipXuEKvr-_F4AaABAg",
            "reply_content": "\u73fe\u5728\u7279\u6548\u90fd\u90a3\u9ebc\u5f37\u55ce\ud83d\ude02"
        },
        {
            "reply_id": "UgwWgsqbbThIwpvBvNB4AaABAg",
            "reply_content": "\u5230\u5e95\u662f\u771f\u7684\u5047\u7684"
        },
        {
            "reply_id": "UgygKU7f2r7WtkiOvPV4AaABAg",
            "reply_content": "\u9019\u500b\u7279\u6548\u592a\u5047\u4e86"
        },
        {
            "reply_id": "UgzSqjlTQe3pk4-BccB4AaABAg",
            "reply_content": "\u6708\u5e95\u65b0\u5403\u6cd5"
        },
        {
            "reply_id": "UgxyCsExtPZZ8XzK7YV4AaABAg",
            "reply_content": "\u5439\u98a8\u6a5f\u597d\u50cf\u4e5f\u53ef\u4ee5\u5439\u5927"
        },
        {
            "reply_id": "UgyCzHF8b6Ad0muVcZR4AaABAg",
            "reply_content": "\u6211\u7b49\u7279\u6548\u7b49\u597d\u4e45 \u7136\u5f8c\u958b\u59cb\u61f7\u7591\u6bcf\u500b\u90e8\u5206\u662f\u4e0d\u662f\u7279\u6548"
        },
        {
            "reply_id": "UgyoXKZS0QW4-MUZVs94AaABAg",
            "reply_content": "\u7279\u6548\u8d85\u771f\u5be6"
        },
        {
            "reply_id": "UgypeU20F_9IjT4zA-p4AaABAg",
            "reply_content": "\u6eff\u5634\u767d\u6fc1\u727d\u7d72"
        }
    ]
}