{
    "video_info": {
        "id": "GBus_M3lB6E",
        "channelTitle": "\u5343\u5343\u9032\u98df\u4e2d",
        "title": "\u3010\u5343\u5343\u9032\u98df\u4e2d\u3011\u9577\u5f97\u8ddf\u5343\u5343\u4e00\u6a23\uff0c\u80c3\u7684\u5bb9\u91cf\u4e5f\u6703\u4e00\u6a23\uff1f\u6c34\u9903PK\u5403\u8d77\u4f86\uff01\u842c\u8056\u7bc0\u649e\u81c9\u610f\u5916\u627e\u5230\u5931\u6563\u591a\u5e74\u7684\u59d0\u59b9\uff1f\uff01\u5343\u7684\u591a\u91cd\u5b87\u5b99",
        "description": "\u7834\u89e3\u90fd\u5e02\u50b3\u8aaa\uff01\n\u9577\u5f97\u4e00\u6a23\u7684\u4eba\u76f8\u898b\u6703\u4e0d\u6703\u632b\u8d77\u4f86\u5462\uff1f \ud83e\udd23\n\u649e\u81c9\u5343\u5343\uff0c\u80c3\u7684\u5bb9\u91cf\u4e5f\u6703\u4e00\u6a23\uff1f\n\u6c34\u9903PK\u5403\u8d77\u4f86\uff01\n\u5927\u5bb6\u89ba\u5f97\u54ea\u4f4d\u4f86\u8cd3\u6700\u50cf\uff1f\n\n\u4f60\u8eab\u908a\u9084\u6709\u8ddf\u6211\u5916\u8c8c\u50cf\u5230\u6703\u88ab\u8aa4\u8a8d\u7684\u670b\u53cb\u55ce\uff1f\n\u8d95\u5feb\u6a19\u8a18\u8d77\u4f86\uff01\n\n#\u5343\u5343\u9032\u98df\u4e2d #\u842c\u8056\u7bc0 #\u591a\u91cd\u5b87\u5b99\n\n\uff0a\uff0a\uff0a\uff0a\uff0a\uff0a\uff0a\uff0a\uff0a\uff0a\uff0a\uff0a\uff0a\uff0a\uff0a\uff0a\uff0a\uff0a\uff0a\uff0a\uff0a\uff0a\n\n\u3010\u7d66\u4f60\u6eff\u6eff\u7684\u60d8\u6328\u8c46\u3011\nhttps://linkfly.to/chienseating\n\u3010\u6211\u6210\u7acb\u7684\u7f8e\u98df\u54c1\u724c - \u6c34\u54e6\u3011 \nhttps://www.suiooh.com/\n\u3010instagram\u3011\nhttps://www.instagram.com/khshu_/\n\u3010twitter\u3011\nhttps://twitter.com/chienshu_tw\n\u3010FB\u7c89\u7d72\u5718\u3011\nhttps://www.facebook.com/Chienseating/",
        "likeCount": "6680",
        "commentCount": "560",
        "viewCount": "466030"
    },
    "comments": [
        {
            "reply_id": "UgxhXEXnPPtOBU5EW2F4AaABAg",
            "reply_content": "\u5927\u5bb6\u4e00\u9910\u53ef\u4ee5\u5403\u5e7e\u9846\u6c34\u9903 \ud83e\udd24"
        },
        {
            "reply_id": "UgyXPmKv2EiMXQL64vt4AaABAg",
            "reply_content": "\u7b2c\u4e00\u500b\u662f\u5074\u81c9\u6709\u50cf"
        },
        {
            "reply_id": "Ugwf6jgy6fiBshEzxI14AaABAg",
            "reply_content": "\u90fd\u4e0d\u50cf\u8036"
        },
        {
            "reply_id": "UgyxJsyZLITOsz8-yil4AaABAg",
            "reply_content": "\u96e3\u5230\u53ea\u6709\u6211\u89ba\u5f97\u5168\u90e8\u90fd\u4e0d\u50cf\u55ce"
        },
        {
            "reply_id": "Ugx_T5QXZPCiOkOpeyx4AaABAg",
            "reply_content": "\u611b\u4f73\u5f88\u6f02\u4eae"
        },
        {
            "reply_id": "Ugxjp_IvjEC79vE7xzh4AaABAg",
            "reply_content": "\u611b\u4f73\u6700\u50cf"
        },
        {
            "reply_id": "UgwaF2wtI6oL3NqtgyR4AaABAg",
            "reply_content": "\u6709\u7407\u4ed4\u7684IG\u9023\u7d50\u55ce\uff1f\u6c92\u6709\u5230\u5f88\u50cf\u4f46\u6a21\u6a23\u548c\u500b\u6027\u90fd\u8d85\u53ef\u611b\uff01"
        },
        {
            "reply_id": "UgwkcyLot2XDXocd7-N4AaABAg",
            "reply_content": "\u963f\u5a77\u5f88\u50cf\u2026 \u90a3\u500b\u8f2a\u5ed3"
        },
        {
            "reply_id": "UgzMXCCmlzo03ZeK4yR4AaABAg",
            "reply_content": "\u597d\u50cf\u770b\u4e86\u5343\u5343\u7248\u7684\u963f\u677e\ud83d\ude02"
        },
        {
            "reply_id": "UgzWPtgaOeI0nquX0m14AaABAg",
            "reply_content": "\u6709\u6c92\u6709\u4eba\u89ba\u5f97\u5f69\u8679\u8001\u5e2b\u9577\u5f97\u597d\u50cf\u96fb\u8996\u5287\u4e09\u5341\u800c\u5df2\u7684\u9867\u4f73\uff1f\uff1f\ud83e\udd14"
        },
        {
            "reply_id": "Ugy_YC0vbdyXjcDkXrp4AaABAg",
            "reply_content": "\u65b0\u5317\u5e02\u6a39\u6797\u5340\u7684\u8b70\u54e1\uff0c\u6d2a\u4f73\u541b\uff0c\u8ddf\u59b3\u8d85\u50cf\u7684\uff01!"
        },
        {
            "reply_id": "Ugw1FC08uDJ6Sg04Yqx4AaABAg",
            "reply_content": "\u90fd\u4e0d\u50cf\u963f\u963f"
        },
        {
            "reply_id": "UgyEolVwfyrMVrvj6ix4AaABAg",
            "reply_content": "\u516b\u9846\u6c34\u9903\u5b8c\u86cb\ud83d\ude2e\ud83d\ude2e\n\u6211\u90fd\u4e8c\u5341\u500b\u8fa3\u5473\u934b\u8cbc\u52a0\u4e00\u500b\u4e7e\u9eb5\u9084\u6709\u8c46\u6f3f\u770b\u5929\u6c23\u559d\u6e6f\ud83d\ude05\ud83d\ude05\ud83d\ude05"
        },
        {
            "reply_id": "Ugx8hHum4cfPzlKTkGJ4AaABAg",
            "reply_content": "\u5f69\u8679\u8001\u5e2b\u597d\u6b63\ud83d\ude05"
        },
        {
            "reply_id": "UgxF_iYIM1nDbr_JsQF4AaABAg",
            "reply_content": "\u7407\u4ed4\u597d\u53ef\u611b\ud83d\ude0d"
        },
        {
            "reply_id": "Ugye3paU0vOVwo3sAbx4AaABAg",
            "reply_content": "\u5403\u6c34\u9903 \u5927\u5bb6\u90fd\u5074\u81c9 \u6bcf\u500b\u90fd\u6709\u795e\u4f3c\u5343\u5343\u7684\u5730\u65b9."
        },
        {
            "reply_id": "Ugxl_zUYuSIcA_4AV8x4AaABAg",
            "reply_content": "\u600e\u9ebc\u6c92\u6709\u8fa6\u5343\u5b87\u5b99\u6b4c\u5531\u5927\u8cfd\ud83d\ude02"
        },
        {
            "reply_id": "UgyJ2E4fsHfnvExhkDt4AaABAg",
            "reply_content": "\u984c\u5916\u8a71 \u5343\u5343\u9019\u96c6\u5507\u8272\u597d\u597d\u770b!!\ud83e\udd29\u60f3\u6572\u7897\u554f\u554f\u5507\u818f\u724c\u5b50\u8272\u865f\u4e86~"
        },
        {
            "reply_id": "UgyGGQukxq8CcF1gdk94AaABAg",
            "reply_content": "\u611b\u4f73\u6700\u50cf\n\u7407\u4ed4\u6211\u89ba\u5f97\u8ddf\u4e9e\u59ae\u6bd4\u8f03\u50cf\ud83e\udd23"
        },
        {
            "reply_id": "UgxKCnizs5n4C4bfT7V4AaABAg",
            "reply_content": "\u611b\u4f73\u6bd4\u5343\u5343\u6f02\u4eae\uff0c\u4e0d\u77e5\u9053\u6703\u4e0d\u6703\u88ab\u8e22\uff1f \u584a\u9676\u554a\uff01"
        }
    ]
}