{
    "video_info": {
        "id": "XrDMZVfY1Sk",
        "channelTitle": "\u5343\u5343\u9032\u98df\u4e2d",
        "title": "\u3010\u5343\u5343\u9032\u98df\u4e2d\u3011\u548c\u7f85\u862d\u5403\u6c38\u548c\u8c46\u6f3f\uff01\u65e5\u672c\u7b2c\u4e00\u7537\u516c\u95dc\u592a\u6703\u64a9\uff0c\u7b2c\u4e00\u6b21\u5403\u9e79\u8c46\u6f3f\u3001\u97ed\u83dc\u76d2\u7684\u53cd\u61c9\u662f\uff1f",
        "description": "\u65e5\u672c\u7b2c\u4e00\u7684\u8fa3\u500b\u7537\u4eba\uff0c\u7f85\u862d\u4f86\u4e86\uff01\n\u9019\u6b21\u627e\u4ed6\u4e00\u8d77\u5403\u53f0\u5f0f\u65e9\u9910\n\u76f4\u63a5\u5728\u73fe\u5834\u914d\u5c0d\u914d\u8d77\u4f86 \ud83e\udd23\n\u9806\u4fbf\u8b93\u4ed6\u8a66\u8a66\u770b\u53ea\u6709\u53f0\u7063\u4eba\u624d\u61c2\u7684\u9e79\u8c46\u6f3f\u548c\u97ed\u83dc\u76d2\u54c8\u54c8\u54c8\n\n\u7f85\u862d\u3055\u3093\u672c\u4eba\u6c23\u5834\u771f\u7684\u8d85\u5f37\n\u4e00\u51fa\u5834\u5c31\u81ea\u5e36\u5de8\u661f\u5149\u74b0 \n\u6574\u500b\u4eba\u90fd\u8d85\u5b8c\u7f8e\u5594\u8cb7\u5c2c \u2764\ufe0f\n\n\u9644\u4e0a\u7f85\u862d\u3055\u3093\u7684\u91d1\u53e5\uff1a\n\u300c\u6240\u8b02\u7684\u81ea\u4fe1\u4e26\u4e0d\u662f\u8207\u751f\u4ff1\u4f86\uff0c\u81ea\u4fe1\u662f\u552f\u6709\u900f\u904e\u52aa\u529b\u624d\u80fd\u7372\u5f97\u7684\u6771\u897f\u3002\u300d\n\u5e0c\u671b\u5927\u5bb6\u90fd\u6709\u548c\u7f85\u862d\u4e00\u6a23\u7684\u5805\u5b9a\u81ea\u4fe1 \u2728\n\n\u3010ROLAND\u81ea\u4fe1\u54f2\u5b78\u3011\u8ab2\u7a0b\u9801\u9023\u7d50\uff1ahttps://www.pressplay.cc/link/070DD813\n\u5373\u65e5\u8d77\u52304/18\uff0c\u5343\u5343\u89c0\u773e\u5c08\u5c6c\u512a\u60e0\u78bc\u3010CHIENROLAND\u3011\u53ef\u6298\u62b5200\u5143\u5537\uff01\n\n#\u7f85\u862d #Roland #\u6c38\u548c\u8c46\u6f3f\n#\u5343\u5343\u9032\u98df\u4e2d\n\n\uff0a\uff0a\uff0a\uff0a\uff0a\uff0a\uff0a\uff0a\uff0a\uff0a\uff0a\uff0a\uff0a\uff0a\uff0a\uff0a\uff0a\uff0a\uff0a\uff0a\uff0a\uff0a\n\n\u3010\u7d66\u4f60\u6eff\u6eff\u7684\u60d8\u6328\u8c46\u3011\nhttps://linkfly.to/chienseating\n\u3010\u6211\u6210\u7acb\u7684\u7f8e\u98df\u54c1\u724c - \u6c34\u54e6\u3011 \nhttps://www.suiooh.com/\n\u3010instagram\u3011\nhttps://www.instagram.com/khshu_/\n\u3010twitter\u3011\nhttps://twitter.com/chienshu_tw\n\u3010FB\u7c89\u7d72\u5718\u3011\nhttps://www.facebook.com/Chienseating/",
        "likeCount": "14949",
        "commentCount": "590",
        "viewCount": "739882"
    },
    "comments": [
        {
            "reply_id": "UgzMbrS6gEnUI8PkYfN4AaABAg",
            "reply_content": "\u5316\u599d\u7f8e\u5bb9\u53c8\u4e0d\u662f\u5973\u4eba\u7684\u5c08\u5229\uff0c\u7537\u751f\u4e5f\u5f88\u611b\u6f02\u4eae"
        },
        {
            "reply_id": "UgxPSlRkl27p3Gjn_vR4AaABAg",
            "reply_content": "\u50cf\u6211\u5403\u71d2\u9905\u90fd\u6703\u6389\u524a\u524a\uff0c\u7f85\u862d\u4ed6\u662f\u600e\u9ebc\u8a13\u7df4\u7684\uff1f\u600e\u9ebc\u5403\u71d2\u9905\u6cb9\u689d\u4e0d\u6703\u6389\u524a\u524a"
        },
        {
            "reply_id": "Ugx9XUcmG43Yr7128Hd4AaABAg",
            "reply_content": "\u65e5\u672c\u4eba\u5403\u4e0d\u6163\u53f0\u7063\u7684\u98df\u7269\uff1f"
        },
        {
            "reply_id": "Ugy7MbhdD9P0qDoZeWR4AaABAg",
            "reply_content": "\u6211\u6bd4\u8f03\u559c\u6b61\u9e79\u8c46\u6f3f\u3001\u71d2\u9905\u6cb9\u689d\u3001\u5c71\u6771\u9945\u982d"
        },
        {
            "reply_id": "UgwZ8Zi9-bYceDTnV6p4AaABAg",
            "reply_content": "\u7576\u7136\u89aa\u5634\u7684\u6642\u5019\uff0c\u7537\u4eba\u5f88\u6015\u5973\u4f34\u5403\u97ed\u83dc\u6c34\u9903"
        },
        {
            "reply_id": "Ugxq_NGOK0ETzxMfLYd4AaABAg",
            "reply_content": "\u7f85\u862d\u9577\u5f97\u597d\u5e25\u5594\uff01"
        },
        {
            "reply_id": "Ugwn4vszqoRk-5pUilV4AaABAg",
            "reply_content": "\u96e3\u602a\u90a3\u4e9b\u5927\u5abd\u90fd\u5fcd\u4e0d\u4f4f\u5077\u5077\u6478\u4f60"
        },
        {
            "reply_id": "Ugyy7Kw7fngfpEsIO854AaABAg",
            "reply_content": "\u53e4\u58b3\u6642\u671f\u7684\u8cb4\u65cf\u5c0f\u738b\u5b50\u7a7f\u8d8a\u5230\u73fe\u4ee3\u65e5\u672c\u7576\u725b\u90ce"
        },
        {
            "reply_id": "Ugz-B9vlFpOLSFLkWih4AaABAg",
            "reply_content": "\u6211\u4e5f\u5f88\u559c\u6b61\u7f85\u862d"
        },
        {
            "reply_id": "UgybCeYcrxbnJaef9ft4AaABAg",
            "reply_content": "\u70ba\u4ec0\u9ebc\u4ed6\u7d93\u5e38\u6234\u58a8\u93e1\uff1f"
        },
        {
            "reply_id": "UgwIFv14OZDr_LxX6Wx4AaABAg",
            "reply_content": "\u5c45\u7136\u5728\u6211\u5bb6\u9644\u8fd1\uff01 \u597d\u60f3\u89aa\u773c\u770b\u7f85\u862d\ud83d\ude2d"
        },
        {
            "reply_id": "UgxVhAjiQp1MOrsIi9h4AaABAg",
            "reply_content": "\u6211\u4ee5\u70ba\u6703\u770b\u5230\u7f85\u862d\u88ab\u5343\u5343\u7684\u98df\u91cf\u5687\u5230\u7684\u756b\u9762\ud83d\ude02"
        },
        {
            "reply_id": "UgxwEFuOKczxSryM9gx4AaABAg",
            "reply_content": "\u7f85\u862d\u597d\u53ef\u611b!!!\u6c92\u6709\u53bb\u4ed6\u7684\u5e97~\u8a9e\u8a00\u4e5f\u6709\u969c\u7919\u55da\u55da:(\u4ed6\u4e00\u5b9a\u8d85\u9999"
        },
        {
            "reply_id": "UgyiOlx6Gc5Gn-zwgIN4AaABAg",
            "reply_content": "\u5343\u5343\u4e5f\u592a\u93ae\u5b9a\u4e86\uff0c\u8981\u662f\u6211\u4e00\u5b9a\u6688\u5012"
        },
        {
            "reply_id": "Ugyo7aRH_0Yv_5_Sfqd4AaABAg",
            "reply_content": "\u7f85\u862d\u53ea\u662f\u500b\u9ad8\u7d1a\u725b\u90ce~~\u54c0\u9019\u793e\u6703\u75c5\u4e86"
        },
        {
            "reply_id": "UgyDzluULFfilTWGg7J4AaABAg",
            "reply_content": "\u6574\u652f\u5f71\u7247\uff0c\u526a\u63a5\u7684\u6709\u5920\u5dee\uff0c\u4e0d\u66c9\u5f97\u5728\u5e79\u561b\ud83d\ude11\ud83d\ude11"
        },
        {
            "reply_id": "UgzExb9ZcYLConbVxuJ4AaABAg",
            "reply_content": "\u525b\u4f86\u53f0\u7063\u7684\u6642\u5019\uff0c\u4e5f\u89ba\u5f97\u9e79\u8c46\u6f3f\u597d\u50cf\u5f88\u5947\u602a\uff0c\u60f3\u8aaa\u8c46\u6f3f\u61c9\u8a72\u662f\u751c\u7684\n\u4f46\u4e00\u8a66\u5c31\u611b\u4e0a\uff0c\u5176\u5be6\u9e79\u7684\u8c46\u6f3f\u7684\u5473\u9053\u6709\u9ede\u50cf\u65e5\u672c\u7684\u8c46\u4e73\u706b\u934b\n\u6211ok\u6211ok"
        },
        {
            "reply_id": "UgwZzFdHWV7I7k_PpRd4AaABAg",
            "reply_content": "\u7f85\u862d\u4ee4\u6211\u5c0d\u516c\u95dc\u6539\u89c0\ud83d\udc4d"
        },
        {
            "reply_id": "Ugzk1G0bBklkSesO0UJ4AaABAg",
            "reply_content": "\u73fe\u5728\u5169\u6027\u5e73\u6b0a \u4ec0\u9ebc\u53eb\u505a\u7537\u751f\u628a\u9019\u5b78\u8d77\u4f86 \u5973\u751f\u505a\u4ec0\u9ebc\u90fd\u662f\u5c0d\u7684\uff1f\u4e82\u8b1b\u4e00\u901a\uff0c\u800c\u4e14\u7f85\u862d\u7684\u610f\u601d\u4e5f\u4e0d\u662f\u9019\u6a23 \u7576\u500byt \u8acb\u5c0f\u5fc3\u767c\u8a00 \u4e0d\u8981\u4e82\u6559"
        },
        {
            "reply_id": "UgxrxXUHCBQ_zJNN8ol4AaABAg",
            "reply_content": "\u7f85\u862d\u771f\u7684\u8d85\u8b9a\u7684 \u7136\u5f8c\u5343\u5343\u975e\u5e38\u7121\u804a \u53ea\u662f\u9644\u548c"
        }
    ]
}