{
    "video_info": {
        "id": "sIbuWJyDyXQ",
        "channelTitle": "Rosalina's Kitchen \u863f\u6f54\u5854\u7684\u5eda\u623f",
        "title": "\u5bb6\u5e38\u756a\u8304\u7092\u86cb\uff5e\u5abd\u5abd\u7684\u5473\u9053\u91cd\u73fe\uff01\uff0b\u852c\u83dc\u9bae\u9b5a\u6e6f\uff0c\u5e74\u5f8c\u7626\u8eab\u5fc5\u5b78\uff01",
        "description": "\u5bb6\u5e38\u756a\u8304\u7092\u86cb\uff5e\u5abd\u5abd\u7684\u5473\u9053\u91cd\u73fe\uff01\uff0b\u852c\u83dc\u9bae\u9b5a\u6e6f\uff0c\u5e74\u5f8c\u7626\u8eab\u5fc5\u5b78\uff01\n\u300e\u863f\u6f54\u5854\u7684\u5eda\u623f\u300f\u852c\u83dc\u9bae\u9b5a\u6e6f\uff06\u756a\u8304\u7092\u86cb \u6e96\u914d\u98df\u6750\n\u852c\u83dc\u9bae\u9b5a\u6e6f\u6e96\u5099\u6750\u6599\uff1a\n\u5305\u5fc3\u767d\u83dc \u4e00\u5c0f\u9846 \u6216\u8005 \u767d\u863f\u8514\u4e00\u5c0f\u689d\n\u7d05\u863f\u8514 \u4e00\u689d \u7d04150~200\u514b\n\u725b\u756a\u8304 \u4e2d\u578b\u4e00\u9846\n\u6d0b\u8525 \u5169\u5c0f\u9846 \u7d04250\u514b\n\u8591\u7247 3~4\u7247\n\u849c\u982d \u7d0425\u514b\n\u849c\u82d7 \u4e00\u682a\n\u897f\u6d0b\u82b9 \u4e00\u652f\n\u9e7d\n\u767d\u80e1\u6912\u7c92or \u9ed1\u80e1\u6912\u7c92 \u4e00\u5c0f\u64ae\n\u6e05\u9152 \u9069\u91cf\n\u51b7\u6c34 1200~1300ml\n\u7121\u8abf\u5473\u7684\u6606\u5e03\u67f4\u9b5a\u9ad8\u6e6f\u5305 \u5169\u5305\n\u5e02\u552e \u9c78\u9b5a\u7247 \u6216\u9bdb\u9b5a\u7247\u4e00\u4efd \uff0c\u6216\u8005\u4efb\u4f55\u559c\u6b61\u7684\u9b5a\u7247\u5747\u53ef\n\n\u756a\u8304\u7092\u86cb \u6e96\u5099\u6750\u6599\uff1a\n\u725b\u756a\u8304 \u4e2d\u5c0f\u578b \u7d045~6\u9846 \u7d04650 \u514b\n\u96de\u86cb  6\u9846\n\u725b\u5976 \u7d0460ml\n\u7cd6 3~5\u514b\uff08\u559c\u6b61\u751c\u4e00\u9ede\u5c31\u591a\u653e\u4e00\u9ede\uff09\n\u6e05\u9152\uff0b\u6c34\uff1d50ml \n\u7206\u9999\u6750\u6599\uff1a\n\u849c\u672b 15\u514b\n\u8766\u76ae \u7d0410~12\u514b\n\u8525\u767d\uff0c\u7d04\u4e09\u682a\u4efd\u91cf\n\u8525\u7da0 \u9069\u91cf\n\n\u2605\u559c\u6b61\u6211\u5275\u4f5c\u7684\u6599\u7406\u5f71\u7247\u55ce\uff1f\u4e0d\u8981\u5fd8\u4e86\u8a02\u95b1\u6211\u7684\u983b\u9053\u5594\uff5e\r\nhttps://www.youtube.com/channel/UCcb9uxCoIgw7RQjQnlgd0Xw\r\n\u8ffd\u8e64\u6211\u7684FACEBOOK: https://www.facebook.com/rosalinakitchen/",
        "likeCount": "4796",
        "commentCount": "109",
        "viewCount": "227613"
    },
    "comments": [
        {
            "reply_id": "Ugy-XmUc4wfiUfqkKUh4AaABAg",
            "reply_content": "\u60a8\u597d\ud83d\ude0a \u8acb\u554f\u716e\u98ef\u7684\u934b\u5177\u662f\u54ea\u4e00\u500b\u724c\u5b50\u5462\uff1f\u8b1d\u8b1d"
        },
        {
            "reply_id": "UgyLotB_GEf8py83Z294AaABAg",
            "reply_content": "\u65e5\u5e38\u8aaa\u8a71\u4e5f\u662f\u9019\u6a23\u7684\u8a9e\u6c23\u8a9e\u8abf\u55ce\uff1f"
        },
        {
            "reply_id": "UgzI0cQlBTumYlihtWJ4AaABAg",
            "reply_content": "\u8acb\u554f\u60a8\u7cd6\u662f\u653e\u7d05\u7cd6\u55ce"
        },
        {
            "reply_id": "UgziFSgiFxyLdyDw76d4AaABAg",
            "reply_content": "\u8acb\u554f\u5854\u5854\u63a8\u85a6\u90a3\u500b\u724c\u5b50\u7684\u7121\u8abf\u5473\u6606\u5e03\u67f4\u9b5a\u9ad8\u6e6f\u5305"
        },
        {
            "reply_id": "Ugwtzc_9oz7YuA3yqbt4AaABAg",
            "reply_content": "\u4eca\u5929\u628a\u5927\u767d\u83dc\u63db\u6210\u9ad8\u9e97\u83dc\u548c\u767d\u863f\u8514\u716e\u4e86\u6e6f\uff0c\u6e6f\u982d\u90fd\u662f\u852c\u83dc\u7684\u751c\u9999\n\u5bb6\u4eba\u4e5f\u8aaa\u5f88\u597d\u559d\uff01\u975e\u5e38\u8b1d\u8b1d\u5854\u5854\u7684\u5f71\u7247\u5206\u4eab\u2764"
        },
        {
            "reply_id": "UgwXpXOseYEBDwbdVTd4AaABAg",
            "reply_content": "\u592a\u592a\u53ef\u4ee5\u5c1d\u8bd5\u7528\u3010\u6cf0\u5f0f\u7ea2\u5496\u55b1\u3011\u6765\u6599\u7406\u756a\u8304\u7092\u86cb\uff0c\u5c31\u5728\u7206\u9999\u8471\u59dc\u7684\u65f6\u5019\u4e00\u5e76\u653e\u5165\u3002\u6709\u6ce8\u610f\u5230\u756a\u8304\u63d0\u524d\u5df2\u7ecf\u53bb\u76ae\u4e86\uff0c\u8bf7\u95ee\u662f\u7528\u70ed\u6c34\u63d0\u524d\u70eb\u8fc7\u4e86\u561b\uff1f\u6211\u7ecf\u5e38\u5c06\u756a\u8304\u70eb\u52308\u6210\u719f\u3002\u8fd9\u6837\u5c31\u4e0d\u7528\u5728\u6700\u540e\u6df7\u5408\u9636\u6bb5\uff0c\u5728\u9505\u4e2d\u52a0\u70ed\u592a\u957f\u65f6\u95f4\u3002\u540c\u65f6\u8fd8\u80fd\u54c1\u5c1d\u5230\uff0c\u7565\u6709\u56bc\u52b2\u7684\u756a\u8304\u98ce\u5473\u3002"
        },
        {
            "reply_id": "Ugzj6SF93CiBnbPEfjt4AaABAg",
            "reply_content": "\u7b2c\u4e00\u6b21\u770b\u5230\u7092\u86cb\u756a\u8304\u8981\u653e\u8766\u7c73\u3001\u5509\u22ef"
        },
        {
            "reply_id": "UgxNvTs84VnSMev2SKB4AaABAg",
            "reply_content": "\u9019\u6e6f\u982d\u61c9\u8a72\u7528\u4ec0\u9ebc\u8089\u90fd\u6703\u5f88\u7f8e\u5473\ud83d\ude0a"
        },
        {
            "reply_id": "Ugyct3i9m8u4-mt7I9t4AaABAg",
            "reply_content": "\u5854\u5854\u771f\u662f\u6211\u770b\u904e\u8b1b\u7684\u6700\u4ed4\u7d30\u597d\u61c2\u7684"
        },
        {
            "reply_id": "UgxjwPsMs5ai8MNrydR4AaABAg",
            "reply_content": "\u8acb\u554f\u9019\u53ea\u934b\u662f\u591a\u5927\uff1f"
        },
        {
            "reply_id": "Ugwtdqa3OcI6W1M77iB4AaABAg",
            "reply_content": "\u6599\u7406\u7684\u904e\u7a0b\u883b\u8b1b\u7a76\u7684\uff0c\u5f88\u7d30\u5fc3\uff0c\u852c\u83dc\u9bae\u9b5a\u6e6f\u6709\u65e5\u5f0f\u6599\u7406\u7684\u98a8\u683c\u3002\u3002"
        },
        {
            "reply_id": "UgytAx-0lAM7lbFmBah4AaABAg",
            "reply_content": "\u770b\u8457\u5c31\u89ba\u5f97\u5e78\u798f"
        },
        {
            "reply_id": "Ugxd624H4navJqB1b8t4AaABAg",
            "reply_content": "\u6211\u5abd\u5abd\u662f\u90fd\u6703\u52a0\u756a\u8304\u91ac"
        },
        {
            "reply_id": "UgzvZbXCPXepUIjL9Fd4AaABAg",
            "reply_content": "\u770b\u8d77\u4f86\u5065\u5eb7\u53c8\u7f8e\u5473\u554a\uff01\u5854\u5854\u8acb\u554f\u4e00\u4e0b\u5f71\u7247\u4e2d\u6e6f\u934b\u7684\u5c3a\u5bf8\u662f\u591a\u5927\u5462\uff1f"
        },
        {
            "reply_id": "UgyB1sIR2E4Bpf921nB4AaABAg",
            "reply_content": "\u5efa\u8b70\u756a\u8304\u4e0d\u8981\u8cb7\u90a3\u7a2e\u8010\u653e\u76ae\u539a\u7684\u54c1\u7a2e\u6703\u5f88\u96e3\u5403"
        },
        {
            "reply_id": "UgxL6HxKZM2Yg7RS7NV4AaABAg",
            "reply_content": "\u60f3\u8981\u8a62\u554f\u59b3\u7528\u7684\u934b\u5b50\u662f\u4ec0\u9ebc\u724c\u5b50\u5462\ud83d\ude0a"
        },
        {
            "reply_id": "UgwUUdS4npQsr0Jca3B4AaABAg",
            "reply_content": "\u4e3b\u6301\u4eba\u8b1b\u8a71\u597d\u50cf\u5f88\u5e74\u8f15\u7684\u6a23\u5b50"
        },
        {
            "reply_id": "Ugy661XdRZ6o6ZyF_ZZ4AaABAg",
            "reply_content": "\u5854\u5854\uff0c\u8acb\u6559\u60a8\u756a\u8304\u7092\u86cb\u662f\u54ea\u500b\u54c1\u724c\u7684\u5462\uff1f\n\u671f\u5f85\u60a8\u56de\u8986\u5594\uff01\n\u8b1d\u8b1d\u60a8"
        },
        {
            "reply_id": "UgzKaTxl9kwF39HEFjl4AaABAg",
            "reply_content": "\u8acb\u554f\u4f60\u7528\u7684\u662f\u4ec0\u9ebc\u9b5a\uff1f"
        },
        {
            "reply_id": "UgzS_TgfviG-tSOOBHt4AaABAg",
            "reply_content": "\u5854\u5854\u8acb\u554f\u53ef\u4ee5\u6559\u7092\u51ac\u7c89\u55ce\uff1f"
        }
    ]
}