{
    "video_info": {
        "id": "Wlm9RYKGPQk",
        "channelTitle": "77\u8001\u5927",
        "title": "\u8170\u75e0\u80cc\u75db\u3001\u80a9\u9838\u75e0\u75db\uff01\u4e00\u6b3e\u795e\u79d8\u4e2d\u85e5\u8336\u98f2\uff0c\u5fc5\u5b78\u4e00\u9031\u6539\u5584\uff01\uff01\u301077\u8001\u5927\u3011",
        "description": "\u4f60\u7d93\u5e38\u8170\u75e0\u80cc\u75db\u55ce\uff1f\n\u6211\u77e5\u9053\u4e00\u5806\u5c08\u5bb6\u5011\u7d66\u59b3\u5011\u7684\u5efa\u8b70\u90fd\u6709\u6548\uff0c\n\u8981\u4f60\u6b63\u78ba\u7684\u5750\u59ff\u3001\u7761\u59ff\u3001\u4e0d\u80fd\u7ff9\u8173\u3001\u4e09\u4e03\u6b65\uff0c\n\u4f46\u60f3\u505a\u5230\u7c21\u76f4\u6bd4\u4e2d\u6a02\u900f\u9084\u8981\u96e3\u3002\n\n\u6240\u4ee5\u8001\u5927\u4eca\u5929\u6559\u4f60\u5011\u6700\u6700\u6700\u7c21\u55ae3\u62db\uff0c\n\u4e56\u4e56\u7167\u8457\u505a\uff0c\u5feb\u901f\u7de9\u89e3+\u6539\u5584\u3002 \n\u5f9e\u6b64\u8b93\u4f60\u8ddf\u8170\u9178\u80cc\u75db\u8aaa\u518d\u898b\uff01\n- - - - - - - - - - - - - - - - - - - - - - - - - - - - - - - - - - - - - - - - - - - - - - - - - - - - - - - - - - - - - - - - - - - - - - - - - - - - - - - - - - - - -\n\u9ad8\u8840\u58d3\u51ac\u5b63\u98c6\u5347\uff0c\u4e2d\u98a8\u3001\u5fc3\u8840\u7ba1\u75be\u75c5\u8d85\u53ef\u6015\uff0c\u8840\u58d3\u8abf\u7406\u4fdd\u547d4\u653b\u7565\uff0c\u5feb\u5206\u4eab\u7d66\u9577\u8f29\u77e5\u9053\uff01\u301077\u8001\u5927\u3011\nhttps://youtu.be/rBmPZs_XEiw\n\n\u9ed1\u773c\u5708\u3001\u773c\u7d0b\u5bb3\u4f60\u770b\u8d77\u4f86\u8d85\u8001\uff014\u62db\u5feb\u901f\u6539\u5584\uff0c3\u5468\u898b\u6548\uff01\u301077\u8001\u5927\u3011\nhttps://youtu.be/pDeoKEKntcU\n- - - - - - - - - - - - - - - - - - - - - - - - - - - - - - - - - - - - - - - - - - - - - - - - - - - - - - - - - - - - - - - - - - - - - - - - - - - - - - - - - - - - -\n\u8ffd\u8e64facebook : https://goo.gl/VjUcJa \n\u8ffd\u8e64instagram : https://www.instagram.com/basil_77777\n\n#\u8170\u9178\u80cc\u75db #\u80a9\u9838\u75e0\u75db #\u4e2d\u91ab #\u6539\u5584 #\u5065\u5eb7 #\u4f4e\u982d\u65cf",
        "likeCount": "1127",
        "commentCount": "51",
        "viewCount": "47293"
    },
    "comments": [
        {
            "reply_id": "UgxhuhKb09J-7s-Uv7t4AaABAg",
            "reply_content": "\u8acb\u554f\u8001\u5927\u53ef\u4ee5\u7528\u96fb\u934b\u55ce\uff1f"
        },
        {
            "reply_id": "UgwPN1rZCeGtN007Q-N4AaABAg",
            "reply_content": "\u5982\u679c\u80a9\u8180\u9178\u75db\uff0c\u6bcf\u6b21\u6309\u90fd\u597d\u50cf\u808c\u8089\u7d27\u7ef7\u90a3\u6837\uff0c\u5e94\u8be5\u8981\u5403\u4ec0\u4e48\uff0c\u53ca\u6309\u4ec0\u4e48\u7a74\u4f4d\u6700\u6709\u6548\u554a\uff1f"
        },
        {
            "reply_id": "UgwqVZt6jk0LwYxeTmN4AaABAg",
            "reply_content": "\u8001\u5927\u4f60\u597d\u53ef\u5426\u51fa\u4e00\u96c6\u5173\u4e8e50\u7f8e\u59e8\u6536\u7ecf\u7684\u8377\u5c14\u8499\u8c03\u7406\u548c\u4fdd\u517b\ud83d\ude0a\ud83d\ude0a"
        },
        {
            "reply_id": "UgxwQ1kz_9g-iH83cU14AaABAg",
            "reply_content": "\u8001\u5927\u554a \u8dea\u6c42\u5c08\u9580\u505a\u80a9\u9838\u75e0\u75db\u7684\u4e2d\u85e5\ud83d\ude2d\ud83d\ude2d"
        },
        {
            "reply_id": "Ugwr_6FOUW-jk3_aVPJ4AaABAg",
            "reply_content": "\u8001\u5927\u8ddf\u59b3\u8acb\u6559\u4e00\u4e0b\u60f3\u751f\u7537\u751f\u53ef\u4ee5\u559d\u4ec0\u9ebc\ud83d\ude02\u8a8d\u771f\u554f"
        },
        {
            "reply_id": "Ugxlv1Ku02LBVNktBCN4AaABAg",
            "reply_content": "\u8acb\u554f\u9019\u5e16\u548c\u4f60\u63a8\u85a6\u843d\u53d1\u7684\u90a3\u5e16\u53ef\u4ee5\u540c\u4e00\u5929\u559d\u55ce\uff1f\u85e5\u6027\u6703\u6709\u885d\u7a81\u55ce\uff1f"
        },
        {
            "reply_id": "UgxzCKdWrmSVCAyDLuZ4AaABAg",
            "reply_content": "\u8001\u5927\uff0c\u8acb\u554f\u6709\u9000\u5316\u6027\u95dc\u7bc0\u708e\u53ef\u4ee5\u559d\u7684\u55ce\uff1f\u9577\u8f29\u819d\u84cb\u4e0d\u8212\u670d\ud83d\ude22\u8b1d\u8b1d"
        },
        {
            "reply_id": "UgwLpP3EvEVhjhnMUJt4AaABAg",
            "reply_content": "\u810a\u690e\u6ed1\u812b\u958b\u5b8c\u5200\u5f8c\u53ef\u4ee5\u559d\u55ce\uff1f"
        },
        {
            "reply_id": "UgyIu5kB7md1xehSy8N4AaABAg",
            "reply_content": "\u8acb\u554f\u54fa\u4e73\u5abd\u5abd\u53ef\u4ee5\u559d\u55ce"
        },
        {
            "reply_id": "UgzTZFcjfciGZ9SRcRp4AaABAg",
            "reply_content": "\u982d\u4e00\u6b21\u716e\u4e2d\u85e5\u8336\u737b\u7d6677\u8001\u5927\u5566\uff0c\u525b\u559d\u4e00\u53e3\u6709\u9ede\u82e6\n\u6162\u6162\u559d\u9084\u4e0d\u932f\u559d"
        },
        {
            "reply_id": "UgynO6QlC5rxHGD7gXN4AaABAg",
            "reply_content": "\u9019\u500b\u8336\u98f2\u5f88\u597d,\u4f46\u5982\u679c\u8981\u52a0\u5f37\u7248\u53ef\u4ee5\u52a0\u6842\u679d\u6e6f,\u6842\u679d\u6e6f\u5167\u5bb9\u81ea\u5df1\u67e5"
        },
        {
            "reply_id": "Ugw6q3R0sh78qSJjOUF4AaABAg",
            "reply_content": "\u53ef\u4e0d\u53ef\u4ee5\u7172\u4e86\u6536\u51b0\u7bb1\u9694\u5929\u559d\uff1f\u6bcf\u5929\u653e\u5de5\u4e86\u5c31\u665a\u4e0a\u624d\u56de\u5230\u5bb6\ud83d\ude29\u767d\u5929\u6c92\u6642\u9593\u7172"
        },
        {
            "reply_id": "UgxoCzRB1RoQ0ZIaVoN4AaABAg",
            "reply_content": "\u8001\u5927,\u8acb\u554f\u4f60\u6240\u6709\u5f71\u7247\u63a8\u85a6\u7684\u5065\u5eb7\u8336\u98f2,\u4e00\u5927\u65e9\u7a7a\u8179\u559d\u53ef\u4ee5\u55ce?"
        },
        {
            "reply_id": "UgySwAh5R2HYQuBQudt4AaABAg",
            "reply_content": "\u8bf7\u95ee\u8001\u5927\uff1a\u65b0\u51a0\u4e2d\u62db\uff08\u5df2\u6253\u4e09\u9488\u75ab\u82d7\uff09\u8f7b\u75c7\uff0c\u522b\u7684\u8fd8\u597d\u4f46\u8170\u7279\u522b\u75db\uff0c\u53ef\u662f\u5904\u4e8e\u54fa\u4e73\u671f\u53ef\u4ee5\u559d\u8fd9\u6b3e\u4e2d\u836f\u6c64\u996e\u5417\uff1f\u8c22\u8c22\ud83d\ude4f"
        },
        {
            "reply_id": "Ugy0TtEWENIhDI2khGh4AaABAg",
            "reply_content": "\u4e45\u5750\u5373\u4ee5\u524d\u5de5\u4f5c\u50b7\u5bb3\uff0c\u73fe\u5728\u8170\u9178\u80cc\u75db\u6642\u4e0d\u6642\u767c\u751f\uff0c\u611f\u8b1d\u8001\u5927\u4ecb\u7d39\u4f86\u559d\u559d\u770b\uff0c\u6062\u5fa9\u72fc\u72d7\u8170"
        },
        {
            "reply_id": "Ugz1AbdExtDhorWaK5l4AaABAg",
            "reply_content": "\u8001\u5927\u6211\u6700\u8fd1\u5f88\u5fd9\u8b1d\u8b1d\u4f60\u5e6b\u5fd9\u5206\u4eab\u9019\u500b\u5f71\u7247\u56e0\u70ba\u6211\u8170\u53ca\u6700\u8fd1\u53ef\u80fd\u5373\u5c07\u5de5\u4f5c\u642c\u91cd\u7269\u5c31\u6703\u6709\u80cc\u75db\u75c7\u72c0"
        },
        {
            "reply_id": "UgzaIRCMd7Ut4Butrlh4AaABAg",
            "reply_content": "\u8b1d\u8b1d\u8001\u5927\u7684\u5f71\u7247\uff0c\u8f9b\u82e6\u60a8\u5011\u4e86\ud83d\ude4f\ud83c\udffb\n\u8eab\u908a\u5f88\u591a\u9577\u8f29\u3001\u670b\u53cb\u8ddf\u6211\uff0c\u56e0\u70ba\u4e0a\u73ed\u4e45\u5750\u6216\u9577\u8f29\u5e74\u7d00\u5927\u90fd\u6709\u8170\u75e0\u6216\u80a9\u9838\u75db\u554f\u984c\u3002\n\u771f\u7684\u7372\u76ca\u826f\u591a\uff0c\u611f\u6069\u2764\ud83d\ude4f\ud83c\udffb"
        },
        {
            "reply_id": "UgxDurY34OcG3DV0EGR4AaABAg",
            "reply_content": "\u9ed1\u829d\u9ebb\u4e38\u5566\uff5e\u6bcf\u65e5\u5169\u7c92\u30023\u661f\u671f\u5927\u4fbf\u597d\u4e86\uff0c\u982d\u9aee\u76ae\u819a\u597d\u4e86\uff0c\u80cc\u9178\u7121\u4e86"
        },
        {
            "reply_id": "Ugw-2dd_K-dqz-qZbUt4AaABAg",
            "reply_content": "\u88dc\u814e\u98df\u7269\u771f\u7684\u8981\u591a\u5403~\u9ed1\u829d\u9ebb\u8ddf\u9ed1\u8c46\u90fd\u662f\u597d\u98df\u7269\u3002\u8001\u5927\u7684\u624b\u52e2\u8d85\u6d6e\u8a87\u7684\uff0c\u771f\u662f\u592a\u53ef\u611b\u5566\uff01"
        },
        {
            "reply_id": "UgyLhFnljDIOstssD_l4AaABAg",
            "reply_content": "\u672a\u770b\u5148\u8b9a"
        }
    ]
}