{
    "video_info": {
        "id": "-4597RMO_Wc",
        "channelTitle": "\u55aa\u5c4d\u8001\u7238",
        "title": "Queen card\uff0c\u5230\u5e95\u662f\u53bb\u5531\u6b4c\u9084\u662f\u8df3\u821e\u554a\ud83d\ude02",
        "description": "",
        "likeCount": "13081",
        "commentCount": "343",
        "viewCount": "449393"
    },
    "comments": [
        {
            "reply_id": "UgymKleFPRDFuNvBG0B4AaABAg",
            "reply_content": "\u5f64\u5f64\u5f88\u4f5c"
        },
        {
            "reply_id": "Ugz_1zzw6ZyzjrJBB_R4AaABAg",
            "reply_content": "\u5979\u5011\u908a\u5531\u908a\u8df3"
        },
        {
            "reply_id": "UgxVLgm_EXyL6th2PlZ4AaABAg",
            "reply_content": "\u8df3\u821e\u8ddf\u5531\u6b4c\u7684\ud83d\ude02"
        },
        {
            "reply_id": "UgzHnZuYlVdS7d_YQ914AaABAg",
            "reply_content": "\u8df3\u821e\u548c\u5531\u6b4c"
        },
        {
            "reply_id": "UgzlMXNrx7quv9pVo-V4AaABAg",
            "reply_content": "\u597d\u55e8\u554a"
        },
        {
            "reply_id": "Ugy60dPN5bwEi2d0cSF4AaABAg",
            "reply_content": "\u6a59\u6a59\u8ddf\u5f64\u5f64\u6597\u597d\u53b2\u5bb3"
        },
        {
            "reply_id": "Ugz-kAQ-mrLGHLsTQNZ4AaABAg",
            "reply_content": "\u5b50\u662f\u6311\u821e\u5e79\u561b\u7b11"
        },
        {
            "reply_id": "UgxZEGnwZv_jVJmAPmN4AaABAg",
            "reply_content": "\u5f64\u5f64\u4f60\u5728\u4e82\u8df3\u55ce"
        },
        {
            "reply_id": "UgyLubYWQqJnRs6wJcp4AaABAg",
            "reply_content": "\u6a59\u6a59\u8df3\u7684\u4e0d\u932f\u5594\u52a0\u6cb9!!!\n\u53e6\u4e00\u4f4d\u9ed1\u8272\u8863\u670d\u7684\u5927\u59d0\u59d0\u4e5f\u8df3\u5f97\u5f97\u5f88\u597d\u52a0\u6cb9!!!"
        },
        {
            "reply_id": "UgxZ7VK0N_vVtNeeMQR4AaABAg",
            "reply_content": "\u9019\u9996\u9084\u6709\u6539\u5236\u53f0\u8a9e\u7248\u7684\u6b4c\u66f2\uff01\u6b20\u5496"
        },
        {
            "reply_id": "Ugyu138ReqKBR_4UMNt4AaABAg",
            "reply_content": "\u8df3\u5f97\u597d\u53b2\u5bb3\ud83c\udf89"
        },
        {
            "reply_id": "UgxPo7Pr7Ey6m-THFqJ4AaABAg",
            "reply_content": "\u6a59\u6a59\u597d\u9ad8\u5594\uff01\u597d\u7fa8\u6155"
        },
        {
            "reply_id": "Ugyz-By5JSBdncOqyMh4AaABAg",
            "reply_content": "\u6a59\u6a59\u597d\u9ad8\u5594\uff5e"
        },
        {
            "reply_id": "Ugyhlm_li3t5I8iRnRN4AaABAg",
            "reply_content": "\u5f64\u5f64\u4e0d\u61c2\u8df3\ud83d\ude44"
        },
        {
            "reply_id": "Ugxo9JZyly3SopmOHu14AaABAg",
            "reply_content": "\u9ed1\u8272\u8863\u670d\u7684\u5973\u751f\u662f\u8ab0\u554a\uff1f"
        },
        {
            "reply_id": "UgwJEJ4l4ju1vTXeXA94AaABAg",
            "reply_content": "\u91c7\u91c7\u662f\u6b63\u5e38"
        },
        {
            "reply_id": "UgxVVVkv_VIHIeENpeN4AaABAg",
            "reply_content": "\ud83c\udf89\u8df3\u5f97\u597d\u53ef\u611b\uff0c\u4e5f\u6c92\u8df3\u5f97\u597d\u53ef\u611b\u6f84\u6f84\u8ddf\u7ae5\u7ae5\u7cbe\u795e\u5f88\u597d"
        },
        {
            "reply_id": "Ugw2B8trzhcmFqXb2fp4AaABAg",
            "reply_content": "\u4ed6\u5011\u90fd\u8df3\u7684\u597d\u597d\u770b\u800c\u4e14\u5f64\u5f64\u9577\u5927\u4e86\u4e5f\u5f88\u4e56\u5594\u800c\u4e14\u9084\u8b8a\u7f8e\u6f84\u6f84\u4e5f\u662f\u4e5f\u8b8a\u7684\u5f88\u7f8e\u6211\u7d66\u4f60\u5011\u9ede\u8b9a\u548c\u8a02\u95b1\u2764\u2764\u2764\u6236\ud83d\udc07\ud83d\ude0d\ud83d\ude18\ud83d\ude1a\ud83d\ude0a\ud83d\ude19\u263a"
        },
        {
            "reply_id": "UgwlFxFgAwVtD3S9v2h4AaABAg",
            "reply_content": "\u54c7\u6211\u559c\u6b61"
        },
        {
            "reply_id": "UgyFLxEks2b0rRL3sZZ4AaABAg",
            "reply_content": "\u53bb\u90a3\u8e66\u8fea\ud83d\ude02"
        }
    ]
}