{
    "video_info": {
        "id": "wjViiXr0usY",
        "channelTitle": "\u55aa\u5c4d\u8001\u7238",
        "title": "\uff082023\u6c96\u7e69\u4e4b\u65c5day1\uff09\u6311\u6230\u7b2c\u4e00\u6b21\u5728\u65e5\u672c\u958b\u8eca\uff0c\u9006\u5411\u3001\u958b\u932f\u8def\u3002\u6c96\u7e69\u771f\u7684\u592a\u7f8e\u5566!!!",
        "description": "gogoout \ud83d\ude99 \u6700\u597d\u7528\u7684\u79df\u8eca\u5e73\u53f0\n\u641c\u5c0b\u3001\u6bd4\u8f03\u79df\u8eca\u5c31\u5728 gogoout.com\n\n\u2714 \u53f0\u7063\u3001\u65e5\u672c\u3001\u97d3\u570b\u71b1\u9580\u9810\u8a02\u4e2d\n\u2714 3 \u5206\u9418\u8a02\u8eca\uff0c\u6700\u5feb 24H \u5f8c\u53d6\u8eca\n\u2714 \u5168\u7403\u8d85\u904e 9 \u5343\u53d6\u8eca\u64da\u9ede\uff0c10 \u842c\u53ef\u79df\u8eca\u8f1b\n\n\u55aa\u5c4d\u8001\u7238\u5c08\u5c6c\u8a3b\u518a\u9023\u7d50\u8d08\u9001 $100 \ud83d\udc49 https://gogoout.pse.is/59szu4\n\n\u6bcf\u9031\u4e8c\u56db\u516d\u665a\u4e0a18:30\u6e96\u6642\u4e0a\u7247~\n\u8a02\u95b1\u55aa\u5c4d\u8001\u7238\uff1ahttps://goo.gl/Dsyej5\n\u8a02\u95b1\u55aa\u5c4d\u8001\u7238\u751f\u6d3b\u983b\u9053\uff1ahttps://is.gd/InjMrh\n\u55aa\u5c4d\u8001\u7238FB\uff1ahttps://www.facebook.com/walkerdad1228\n\u55aa\u5c4d\u8001\u7238IG\uff1ahttps://www.instagram.com/walkerdad1228/\nJoanne\uff08\u6a59\u5abd\uff09IG\uff1ahttps://www.instagram.com/joan19990627/\n\u6a59\u6a59IG\uff1ahttps://www.instagram.com/0417eva/\n\u5546\u6848\u5408\u4f5c\uff1awalkerdad1228@capsuleinc.cc\n\n\n\u5fae\u96fb\u5f71\uff1ahttps://goo.gl/tA7WGq\n\u72c0\u6cc1\u5287\uff1ahttps://goo.gl/jD65hB\n\u8718\u86db\u5973\u5b69 Spider Girl\uff1ahttps://is.gd/KPKMfR\n\u641e\u7b11\u7cfb\u5217\uff1ahttps://goo.gl/MV3iTT\n\u98ef\u5e97\u7cfb\u5217\uff1ahttps://is.gd/3vI0ws\n\u958b\u7bb1\u7cfb\u5217\uff1ahttps://goo.gl/BQAbKR\n\u7f8e\u98df\u7cfb\u5217\uff1ahttps://goo.gl/hAEjHn\n\u65e5\u5e38\u7cfb\u5217\uff1ahttps://goo.gl/tTfGx2\nCover\uff1ahttps://reurl.cc/Ov3omg\nCover\u82b1\u7d6e\uff1ahttps://reurl.cc/2LGOlm\n\u5ee2\u5230\u7b11\u7cfb\u5217\uff1ahttps://goo.gl/VMajeF\n\u5317\u6d77\u9053\u4e4b\u65c5\uff1ahttps://goo.gl/GMxYoe\n\u6771\u4eac\u4e4b\u65c5\uff1ahttps://pse.is/NRVCY\n\u6311\u6230\u7cfb\u5217\uff1ahttps://is.gd/EtjO0r\n\u6280\u80fd\u6311\u6230\u8cfd\uff1ahttps://reurl.cc/nL6x42\n\u6574\u4eba\u7cfb\u5217\uff1ahttps://is.gd/LfkM1A\n\u6a59\u6a59\u5eda\u623f\uff1ahttps://is.gd/OnIuzb\n\u5f64\u5f64\u5eda\u623f\uff1ahttps://is.gd/fkksAz\n\u6a59\u7238\u5eda\u623f\uff1ahttps://is.gd/bp9z1K",
        "likeCount": "2439",
        "commentCount": "204",
        "viewCount": "146180"
    },
    "comments": [
        {
            "reply_id": "Ugx7pwGQCZNXkdnkJsp4AaABAg",
            "reply_content": "\u4f60\u5011\u53bb\u7684\u5730\u65b9\u8ddf\u6211\u53bb\u6c96\u7e69\u7684\u5e7e\u4e4e\u4e00\u6a23"
        },
        {
            "reply_id": "Ugz8vIdi0b64zWFn-lt4AaABAg",
            "reply_content": "\u6211\u5011\u53bb\u65e5\u672c\u4e5f\u662f\u4f4f\u9019\u9593\u98ef\u5e97\u4e00\u6a21\u4e00\u6a23\ud83d\ude02\ud83d\ude02\ud83d\ude02"
        },
        {
            "reply_id": "Ugw-r33xRfjEMQv7pkx4AaABAg",
            "reply_content": "\u6c96\u7e69\u6d77\u6d0b\u9928\u600e\u9ebc\u9577\u7684\u4e0d\u4e00\u6a23\u4e86\uff0c\u5916\u89c0\u8ddf\u6211\u524d\u5e7e\u5e74\u53bb\u90fd\u4e0d\u4e00\u6a23\u4e86\uff0c\u61c9\u8a72\u53ea\u6709\u4e00\u9593\u6d77\u6d0b\u9928\u5427\uff1f\u9084\u662f\u6211\u592a\u4e45\u6c92\u53bb\u73a9\u4e86\ud83d\ude02\ud83d\ude02"
        },
        {
            "reply_id": "UgyXHDGPP4cRn81EuKd4AaABAg",
            "reply_content": "\u53ef\u4ee5\u6765\u9a6c\u6765\u897f\u4e9a\u5417\uff0c\u6211\u5973\u513f\u5f88\u5e0c\u671b\u4f60\u4eec\u53ef\u4ee5\u6765\u9a6c\u6765\u897f\u4e9a\u67d4\u4f5b"
        },
        {
            "reply_id": "UgxwVR02mTCSugLsnfx4AaABAg",
            "reply_content": "\u597d\u5947\u5f64\u5f64\u8ddf\u6a59\u6a59\u4e0d\u7528\u4e0a\u8ab2\u55ce\uff1f\ud83d\ude0a\u5f64\u5f64\u771f\u7684\u597d\u53ef\u611b\uff01\u2764\u6a59\u6a59\u771f\u7684\u8d85\u7f8e\u7684\u2764"
        },
        {
            "reply_id": "UgxvHxCvsusiDyun6Z94AaABAg",
            "reply_content": "\u6a59\u6a59\u597d\u6f02\u4eae\u54e6\n\u5f64\u5f64\u597d\u53ef\u611b"
        },
        {
            "reply_id": "Ugw48l_SjktaH-TsMKR4AaABAg",
            "reply_content": "\u6211\u9019\u500b\u6691\u5047\u6211\u53bb\u904e\u6c96\u7e69\uff0c\u548c\u4f60\u5011\u7684\u65c5\u884c\u5f88\u50cf"
        },
        {
            "reply_id": "UgwILBrlsIpP5h6syvd4AaABAg",
            "reply_content": "\u4e0d\u662f\u53f3\u99d5\u55ce"
        },
        {
            "reply_id": "UgzZHpaua3EJPmo7_7l4AaABAg",
            "reply_content": "\u592a\u5de7\u4e86\uff0c\u6a59\u6a59\u624b\u4e0a\u90a3\u96bb\u7ae0\u9b5a\u6211\u525b\u597d\u6709"
        },
        {
            "reply_id": "Ugx6V1ALkiW4wmzL_J94AaABAg",
            "reply_content": "\u597d\u4e45\u6c92\u6709\u7559\u8a00\u4e86\uff0c\u771f\u7684\u662f\u5f88\u611b\u4f60\u5011\u2764"
        },
        {
            "reply_id": "UgzXqJ2NjSNie3XAWfl4AaABAg",
            "reply_content": "\u4f60\u5011\u53bb\u65e5\u672c\u883b\u591a\u6b21\u7684\uff0c\u597d\u597d\u5594\uff01\u4e0b\u6b21\u6a59\u6a59\u4e5f\u4e00\u5b9a\u6703\u626e\u7684\u5f88\u7f8e!!!\u5f64\u5f64\u8ddf\u6a59\u6a59\u90fd\u9577\u5927\u4e86\u4e0d\u5c11\uff0c\u7e7c\u7e8c\u62cd\u66f4\u597d\u7684\u7db2\u7f8e\u7167\u5594\uff01\u6a59\u6a59!"
        },
        {
            "reply_id": "Ugx_2XdBDVbb0un-xFB4AaABAg",
            "reply_content": "\u795d\u4f60\u5011\u5728\u6c96\u7e69\u73a9\u5f97\u6109\u5feb\u55aa\u5c4d\u8001\u7238\u6c96\u7e69\u4e4b\u65c5"
        },
        {
            "reply_id": "UgwWSFRQZO_tCOF3jqV4AaABAg",
            "reply_content": "\u55aa\u5e2b\u8001\u7238\u6c96\u795e\u65c5\u90e8\u904a"
        },
        {
            "reply_id": "UgytlOX6YJYLH12CTO94AaABAg",
            "reply_content": "\u55aa\u5e2b\u8001\u7238"
        },
        {
            "reply_id": "Ugz_rezzQ1HeK5m39FN4AaABAg",
            "reply_content": "\u6211\u4e5f\u6709\u53bb\u6c96\u7e69"
        },
        {
            "reply_id": "Ugz0rs3y3HBTN0xXq3B4AaABAg",
            "reply_content": "\u5f88\u597d\u5947\u6a59\u6a59\u5728\u5b78\u6821\u6709\u559c\u6b61\u7684\u4eba\u55ce\uff1f\ud83d\ude02"
        },
        {
            "reply_id": "Ugw6dUKxKhNQqRRiBFt4AaABAg",
            "reply_content": "\u5927\u5973\u5152\u597d\u597d\u770b"
        },
        {
            "reply_id": "UgwBsceETZ9A_DAVUmN4AaABAg",
            "reply_content": "\u8acb\u554f\u90a3\u500b\u767d\u8272\u6709\u62c9\u934a\u7684\u8cfc\u7269\u888b\u54ea\u88e1\u8cb7\uff1f\u8b1d\u8b1d"
        },
        {
            "reply_id": "UgyowJrmiDjuOqf8lvp4AaABAg",
            "reply_content": "\u6a59\u6a59\u5f64\u5f64\u771f\u7684\u5f88\u5e78\u798f\u8981\u597d\u597d\u73cd\u60dc\u7238\u5abd\u2764\u2764 \u6211\u8d85\u60f3\u53bb\u6c96\u7e69\ud83d\ude0a\ud83d\ude0a"
        },
        {
            "reply_id": "Ugwrod3DhoiMKwLCPh54AaABAg",
            "reply_content": "\u6709\u53bb\u627e\u599e\u599e\u5417\uff1f"
        }
    ]
}