{
    "video_info": {
        "id": "WPccQci7kzA",
        "channelTitle": "J-Bao\u8ce4\u8446",
        "title": "\u3010\u5730\u7344\u6311\u6230\u3011\u518d\u5ea6\u8207\u677e\u9f20\u751c\u871c\u7d04\u6703\uff1f\u58d3\u529b\u592a\u5927\uff01\u7a81\u7136\u5f9e\u300e40\u516c\u5c3a\u540a\u6a4b\u300f\u5f80\u4e0b\u8df3\uff01\uff01\uff01",
        "description": "\u6c92\u60f3\u5230\u6703\u6709\u7b2c\u4e8c\u96c6\uff01\n\ud83d\udc3f\u5b78\u59b9IG \u25ba\u25bahttps://www.instagram.com/hxy_0817/\n\ud83d\ude0e\u8ce4\u8446IG \u25ba\u25bahttps://www.instagram.com/jbao_5000/\n\u300e\u7279\u5225\u611f\u8b1d\u300f\n\u570b\u969b\u9ad8\u7a7a\u5f48\u8df3\uff1ahttps://www.facebook.com/BungeeTW",
        "likeCount": "49258",
        "commentCount": "2564",
        "viewCount": "2174479"
    },
    "comments": [
        {
            "reply_id": "UgwBMgLNckJRE5T8SOJ4AaABAg",
            "reply_content": "\u89e3\u5f97\u5f88\u719f\u7ec3\u554a\uff0c\u7ecf\u5e38\u7684\u5427"
        },
        {
            "reply_id": "Ugw2sS2Cu4UYIKqW9sN4AaABAg",
            "reply_content": "\u6572\u7897\u7b2c\u4e09\u96c6"
        },
        {
            "reply_id": "UgzZ35gdFXE84sypHcN4AaABAg",
            "reply_content": "\u677e\u9f20\u662f\u6211\u8ba4\u4e3a\u8446\u54e5\u4e09\u540e\u5bab\u59b9\u91cc\u6700\u53ef\u7231\u7684\u561e\ud83e\udd23\ud83e\udd23\u6240\u4ee5\u6c42\u8446\u54e5\u4e0d\u8981\u65e0\u89c6\u677e\u9f20\u4e86\u5979\u8fd9\u4e48\u53ef\u7231qwq\u4e0d\u5fcd\u5fc3\u770b\u5230\u5979\u88ab\u65e0\u89c6\u6b38qwq"
        },
        {
            "reply_id": "UgxsIfjKRxVP9RwUWYp4AaABAg",
            "reply_content": "\u677e\u9f20\u53ef\u611b\u53c8\u52c7\u6562\ud83d\ude01\u677e\u9f20\u5728\u4e0b\u9762\u958b\u5fc3\u5f97\u54ed\u8446\u54e5\u5728\u4e0a\u9762\u72c2\u7b11"
        },
        {
            "reply_id": "UgzC6pyDQy57X_GSJml4AaABAg",
            "reply_content": "\u4ec0\u9ebc\u6b4c\u963f\uff1f"
        },
        {
            "reply_id": "UgzZQKmmJsOu9qddMV94AaABAg",
            "reply_content": "\u7adf\u7136\u662f\u8349\u5c6f \u6211\u5c31\u5728\u8349\u5c6f\u96e3\u602a\u89ba\u5f97\u52a0\u6cb9\u7ad9\uff08\u96d9\u51ac\uff09\u8ddf\u5168\u806f\u5f88\u719f\u6089\uff01"
        },
        {
            "reply_id": "UgxAzObrEotZCeRkpFB4AaABAg",
            "reply_content": "\u6700\u8fd1\u525b\u770b\u9019\u500b\u983b\u9053\uff0c\u7d50\u679c\u5fcd\u4e0d\u4f4f\u5237\u4e86\u4e00\u500b\u9031\u672b\u22ef\u22ef\u22ef \u7d55\u5c0d\u662f\u53f0\u7063\u6700\u597d\u770b\u7684yt"
        },
        {
            "reply_id": "Ugxs8ma5MhDKDDbSZlh4AaABAg",
            "reply_content": "\u6211\u525b\u525b\u624d\u767c\u73fe\u9019\u5728\u6211\u5bb6\u9644\u8fd1\u311f \u90a3\u500b\u52a0\u6cb9\u7ad9 \u548c\u99d5\u8a13\u73ed\ud83e\udd23\ud83e\udd23\ud83e\udd23\u7136\u5f8c\u90a3\u9593\u52a0\u6cb9\u7ad9\u5df2\u7d93\u6709\u5145\u96fb\u7684\u4e86"
        },
        {
            "reply_id": "Ugz6PCGUSXSrJL_9i194AaABAg",
            "reply_content": "\u677e\u9f20\u5f88\u53ef\u611b\u2764"
        },
        {
            "reply_id": "Ugz8y0QHaV7l6PXPMRJ4AaABAg",
            "reply_content": "\u6211\u5f88\u597d\u5947\u677e\u9f20\u5728\u8ce4\u8446\u6d17\u6fa1\u4f60\u6642\u5019\u885d\u9032\u53bb\u6709\u770b\u5230\u4ed6\u7684\u3110\u3127\u3110\u3127\u55ce\ud83d\ude02"
        },
        {
            "reply_id": "UgxcmoxC_hkGNNnBpQl4AaABAg",
            "reply_content": "\u4f60\u5011\u6709\u4f86\u8349\u5c6f\ud83d\ude2e\u6211\u4e5f\u5728\u8349\u5c6f\ud83d\ude03"
        },
        {
            "reply_id": "UgyntAndEQNzdRX_aB14AaABAg",
            "reply_content": "\u4f60\u5011\u90a3\u908a\u662f\u6307\u5357\u5bae\u90a3\u4f60\u5011\u90a3\u908a\u662f\u4e0d\u662f\u5c31\u6709\u6d77\u76dc\u6751"
        },
        {
            "reply_id": "UgyHV53o8YfCjFGZDrl4AaABAg",
            "reply_content": "\u6211\u8ddf\u300c\u54c1\u5c91\u59ca\u59ca\u300d\u5dee\u4e00\u500b\u5b57\u800c\u5df2\u311f"
        },
        {
            "reply_id": "Ugxf1p0b9LcNiNLRX4R4AaABAg",
            "reply_content": "\u6211\u4f4f\u9019\u6b38\ud83d\ude02"
        },
        {
            "reply_id": "UgwWYb4BVkgklkOetGd4AaABAg",
            "reply_content": "\u6f14\u7b97\u6cd5\u628a\u6211\u5e36\u56de\u4e00\u5e74\u524d! \u677e\u9f20\u5927\u5927\u771f\u7684\u5f88\u52c7\u6562"
        },
        {
            "reply_id": "Ugxml55HwsVIkbQq9x14AaABAg",
            "reply_content": "\u559c\u52d2\u9760\u5317"
        },
        {
            "reply_id": "UgxMbPsrQJ0X-tjzuxV4AaABAg",
            "reply_content": "\u6211\u9700\u8981\u7b2c\u4e09\u96c6"
        },
        {
            "reply_id": "UgxjyLcblUgxCZeqsc14AaABAg",
            "reply_content": "\u4f60\u8fd8\u8bb0\u5f97\u6709B\u7ad9\u8d26\u53f7\u54e6\uff1f"
        },
        {
            "reply_id": "Ugz8lRUmpQUOF4YOSQV4AaABAg",
            "reply_content": "\u4f60\u5011\u5728\u54ea\u88e1\u8df3\u7684"
        },
        {
            "reply_id": "Ugx6XoCnZb_H-4yDLah4AaABAg",
            "reply_content": "\u4f60\u5011\u5728\u54ea\u88e1\u8df3\u7684"
        }
    ]
}